randomcropclassselective/__init__.py
randomcropclassselective/random_crop_class_selective.py
randomcropclassselective-0.0.1.dist-info/METADATA
randomcropclassselective-0.0.1.dist-info/WHEEL
randomcropclassselective-0.0.1.dist-info/licenses/LICENSE
randomcropclassselective-0.0.1.dist-info/RECORD
