Metadata-Version: 2.4
Name: randomcropclassselective
Version: 0.0.1
Summary: A custom Albumentations transform allowing random crops while preserving specific classes.
Project-URL: Homepage, https://github.com/derekchai/randomcropclassselective
Project-URL: Issues, https://github.com/derekchai/randomcropclassselective/issues
Author-email: Derek Chai <chderek9@gmail.com>
License-Expression: MIT
License-File: LICENSE
Classifier: Operating System :: OS Independent
Classifier: Programming Language :: Python :: 3
Requires-Python: >=3.9
Requires-Dist: albumentations>=2.0.0
